{
"type": "FeatureCollection",
"name": "starting_point",
"crs": { "type": "name", "properties": { "name": "urn:ogc:def:crs:OGC:1.3:CRS84" } },
"features": [
{ "type": "Feature", "properties": { "id": 1, "volume": 1590628 }, "geometry": { "type": "Point", "coordinates": [ 115.503037846194857, -8.34116557928086 ] } }
]
}
